odoo/addons/web_send_message_popup/README.rst
odoo/addons/web_send_message_popup/__init__.py
odoo/addons/web_send_message_popup/__manifest__.py
odoo/addons/web_send_message_popup/i18n/fa.po
odoo/addons/web_send_message_popup/i18n/it.po
odoo/addons/web_send_message_popup/i18n/web_send_message_popup.pot
odoo/addons/web_send_message_popup/readme/CONTRIBUTORS.rst
odoo/addons/web_send_message_popup/readme/DESCRIPTION.rst
odoo/addons/web_send_message_popup/static/description/icon.png
odoo/addons/web_send_message_popup/static/description/index.html
odoo/addons/web_send_message_popup/static/src/js/chatter.js
odoo/addons/web_send_message_popup/templates/assets.xml
odoo14_addon_web_send_message_popup-14.0.1.0.1.dev6.dist-info/METADATA
odoo14_addon_web_send_message_popup-14.0.1.0.1.dev6.dist-info/WHEEL
odoo14_addon_web_send_message_popup-14.0.1.0.1.dev6.dist-info/top_level.txt
odoo14_addon_web_send_message_popup-14.0.1.0.1.dev6.dist-info/RECORD
